{
  "name": "Чеснок",
  "icon": "dragncrops:garlic",
  "category": "dragncrops:crop_category",
  "pages": [
    {
      "type": "patchouli:text",
      "text": "$(l)Тип: $()Корнеплод $(br)$(l)Появляется в: $()Леса"
    },
    {
      "type": "patchouli:spotlight",
      "item": {
        "item": "dragncrops:garlic"
      },
      "text": "Используется как приправа или консервант во многих различных солёных рецептах.",
      "title": "Чеснок"
    },
    {
      "type": "patchouli:multiblock",
      "name": "Чеснок",
      "multiblock": {
        "pattern": [
          [ "0" ],
          [ "1" ]
        ],
        "mapping": {
          "0": "dragncrops:garlic[age=7]",
          "1": "minecraft:grass_block"
        }
      }
    }
  ]
}